DataSourceService/__init__.py
DataSourceService/__main__.py
DataSourceService/anecdotica.py
DataSourceService/api.py
DataSourceService/const.py
DataSourceService/service.py
DataSourceService/test.py
DataSourceService/tools.py
pih_ds-1.41.dist-info/METADATA
pih_ds-1.41.dist-info/WHEEL
pih_ds-1.41.dist-info/entry_points.txt
pih_ds-1.41.dist-info/top_level.txt
pih_ds-1.41.dist-info/RECORD
