Metadata-Version: 2.1
Name: pih-ds
Version: 1.41
Summary: PIH Data storage and source service package
Home-page: https://pacifichosp.com/
Author: Nikita Karachentsev
Author-email: it@pacifichosp.com
License: MIT
Requires-Dist: ipih
